mmd_bot/PostData.py
mmd_bot/WebAdress.py
mmd_bot/__init__.py
mmd_bot/mmd_bot.py
mmd_bot/sendserver.py
mmd_bot/Configs/__init__.py
mmd_bot-0.0.1.dist-info/LICENCE
mmd_bot-0.0.1.dist-info/METADATA
mmd_bot-0.0.1.dist-info/WHEEL
mmd_bot-0.0.1.dist-info/top_level.txt
mmd_bot-0.0.1.dist-info/RECORD
