Metadata-Version: 2.1
Name: mmd-bot
Version: 0.0.1
Summary: mmd_bot Library For Rubika Messenger
Home-page: https://github.com/alitektanus/MMD_BOT
Author: MMD_BOT
Author-email: pyRubiCo@gmail.com
License: MIT
Keywords: messenger,python2,python,python3,api,self,Rubika,rubika,bot,robot,library,rubikalib,rubikalibrary,rubika.ir,m.rubika.ir
Classifier: Development Status :: 5 - Production/Stable
Classifier: Intended Audience :: Developers
Classifier: Natural Language :: English
Classifier: License :: OSI Approved :: GNU Lesser General Public License v3 (LGPLv3)
Classifier: Operating System :: OS Independent
Classifier: Programming Language :: Python
Classifier: Programming Language :: Python :: 3
Classifier: Programming Language :: Python :: 3.5
Classifier: Programming Language :: Python :: 3.6
Classifier: Programming Language :: Python :: 3.7
Classifier: Programming Language :: Python :: 3.8
Classifier: Programming Language :: Python :: 3.9
Classifier: Programming Language :: Python :: 3.10
Classifier: Programming Language :: Python :: 3.11
Classifier: Programming Language :: Python :: Implementation
Classifier: Programming Language :: Python :: Implementation :: CPython
Classifier: Programming Language :: Python :: Implementation :: PyPy
Classifier: Topic :: Internet
Classifier: Topic :: Communications
Classifier: Topic :: Communications :: Chat
Classifier: Topic :: Software Development :: Libraries
Classifier: Topic :: Software Development :: Libraries :: Python Modules
Classifier: Topic :: Software Development :: Libraries :: Application Frameworks
Requires-Python: ~=3.11
License-File: LICENCE
Requires-Dist: requests
Requires-Dist: urllib3
Requires-Dist: pycryptodome
Requires-Dist: colorama
Requires-Dist: tinytag
